{
  "user_rank": "E-6",
  "user_years_of_service": 20,
  "user_career_field": "Operations Research",
  "user_separation_date": "2026-06-01",
  "user_marital_status": "Married",
  "user_dependents": 1,
  "user_service_branch": "Navy",
  "user_locality": "Arlington",
  "user_state": "VA",
  "military_pension_gross": 4425,
  "current_military_takehome_monthly": 8000,
  "medical_plan": "Tricare Prime",
  "vision_plan": "Tricare Vision",
  "dental_plan": "Tricare Dental",
  "_saved_at": "2026-03-23T16:42:40.288422",
  "_scenario_name": "scenario_E-6_20260323_164240"
}